manim_meshes/__init__.py
manim_meshes/data/models/armadillo.ply
manim_meshes/data/models/suzanne.ply
manim_meshes/data/models/tail_topper.stl
manim_meshes/decorators.py
manim_meshes/delaunay/__init__.py
manim_meshes/delaunay/delaunay_criterion.py
manim_meshes/delaunay/divide_and_conquer.py
manim_meshes/delaunay/voronoi.py
manim_meshes/exceptions.py
manim_meshes/helpers.py
manim_meshes/models/__init__.py
manim_meshes/models/data_models/__init__.py
manim_meshes/models/data_models/mesh.py
manim_meshes/models/manim_models/__init__.py
manim_meshes/models/manim_models/basic_mesh.py
manim_meshes/models/manim_models/opengl_mesh.py
manim_meshes/models/manim_models/triangle_mesh.py
manim_meshes/params.py
manim_meshes/shaders/mesh/frag.glsl
manim_meshes/shaders/mesh/geom.glsl
manim_meshes/shaders/mesh/vert.glsl
manim_meshes/templates.py
manim_meshes/types.py
manim_meshes-0.0.8.dist-info/entry_points.txt
manim_meshes-0.0.8.dist-info/LICENSE
manim_meshes-0.0.8.dist-info/WHEEL
manim_meshes-0.0.8.dist-info/METADATA
manim_meshes-0.0.8.dist-info/RECORD
