Metadata-Version: 2.1
Name: manim-meshes
Version: 0.0.8
Summary: rendering 2D and 3D Meshes with manim for displaying and educational Purposes.
Home-page: https://github.com/bmmtstb/manim-meshes
License: MIT
Keywords: animation,manim,trimeshes,mesh
Author: Brizar
Author-email: martin.steinborn@stud.tu-darmstadt.de
Requires-Python: ==3.8.18
Classifier: License :: OSI Approved :: MIT License
Classifier: Programming Language :: Python :: 3
Requires-Dist: ManimPango (>=0.4.1,<0.5.0)
Requires-Dist: decorator (>=5.0.9,<6.0.0)
Requires-Dist: manim (>=0.16.0,<0.17.0)
Requires-Dist: manimgl (>=1.6.1,<2.0.0)
Requires-Dist: moderngl
Requires-Dist: numpy (>=1.24.0,<2.0.0)
Requires-Dist: trimesh (>=3.12.5,<4.0.0)
Project-URL: Repository, https://github.com/bmmtstb/manim-meshes
